[
    {
        "Accession": "MK995302",
        "Country": "Bangladesh",
        "RecordYear": 2019,
        "IsolateYear": "Not available",
        "Host": "Bat",
        "Specimen": "Not available",
        "IsolateName": "25Urine",
        "SeqLength": 224,
        "NonClinical": ""
    },
    {
        "Accession": "MK995301",
        "Country": "Bangladesh",
        "RecordYear": 2019,
        "IsolateYear": "Not available",
        "Host": "Bat",
        "Specimen": "Not available",
        "IsolateName": "1290676TS",
        "SeqLength": 224,
        "NonClinical": ""
    },
    {
        "Accession": "MK995300",
        "Country": "Bangladesh",
        "RecordYear": 2019,
        "IsolateYear": "Not available",
        "Host": "Bat",
        "Specimen": "Not available",
        "IsolateName": "1290659TS",
        "SeqLength": 224,
        "NonClinical": ""
    },
    {
        "Accession": "MK995299",
        "Country": "Bangladesh",
        "RecordYear": 2019,
        "IsolateYear": "Not available",
        "Host": "Bat",
        "Specimen": "Not available",
        "IsolateName": "1290629RS",
        "SeqLength": 224,
        "NonClinical": ""
    },
    {
        "Accession": "MK995298",
        "Country": "Bangladesh",
        "RecordYear": 2019,
        "IsolateYear": "Not available",
        "Host": "Bat",
        "Specimen": "Not available",
        "IsolateName": "21U",
        "SeqLength": 224,
        "NonClinical": ""
    },
    {
        "Accession": "MK995297",
        "Country": "Bangladesh",
        "RecordYear": 2019,
        "IsolateYear": "Not available",
        "Host": "Bat",
        "Specimen": "Not available",
        "IsolateName": "70RU",
        "SeqLength": 224,
        "NonClinical": ""
    },
    {
        "Accession": "MK995296",
        "Country": "Bangladesh",
        "RecordYear": 2019,
        "IsolateYear": "Not available",
        "Host": "Bat",
        "Specimen": "Not available",
        "IsolateName": "45RU",
        "SeqLength": 224,
        "NonClinical": ""
    },
    {
        "Accession": "MK995295",
        "Country": "Bangladesh",
        "RecordYear": 2019,
        "IsolateYear": "Not available",
        "Host": "Bat",
        "Specimen": "Not available",
        "IsolateName": "17_RU",
        "SeqLength": 224,
        "NonClinical": ""
    },
    {
        "Accession": "MK995294",
        "Country": "Bangladesh",
        "RecordYear": 2019,
        "IsolateYear": "Not available",
        "Host": "Bat",
        "Specimen": "Not available",
        "IsolateName": "4417_RU",
        "SeqLength": 224,
        "NonClinical": ""
    },
    {
        "Accession": "MK995293",
        "Country": "Bangladesh",
        "RecordYear": 2019,
        "IsolateYear": "Not available",
        "Host": "Bat",
        "Specimen": "Not available",
        "IsolateName": "4416_RU",
        "SeqLength": 224,
        "NonClinical": ""
    },
    {
        "Accession": "MK995292",
        "Country": "Bangladesh",
        "RecordYear": 2019,
        "IsolateYear": "Not available",
        "Host": "Bat",
        "Specimen": "Not available",
        "IsolateName": "18RU",
        "SeqLength": 224,
        "NonClinical": ""
    },
    {
        "Accession": "MK995291",
        "Country": "Bangladesh",
        "RecordYear": 2019,
        "IsolateYear": "Not available",
        "Host": "Bat",
        "Specimen": "Not available",
        "IsolateName": "4664_RU",
        "SeqLength": 224,
        "NonClinical": ""
    },
    {
        "Accession": "MK995290",
        "Country": "Bangladesh",
        "RecordYear": 2019,
        "IsolateYear": "Not available",
        "Host": "Bat",
        "Specimen": "Not available",
        "IsolateName": "4736_U",
        "SeqLength": 224,
        "NonClinical": ""
    },
    {
        "Accession": "MK995289",
        "Country": "Bangladesh",
        "RecordYear": 2019,
        "IsolateYear": "Not available",
        "Host": "Bat",
        "Specimen": "Not available",
        "IsolateName": "55U",
        "SeqLength": 224,
        "NonClinical": ""
    },
    {
        "Accession": "MK995288",
        "Country": "Bangladesh",
        "RecordYear": 2019,
        "IsolateYear": "Not available",
        "Host": "Bat",
        "Specimen": "Not available",
        "IsolateName": "87U",
        "SeqLength": 224,
        "NonClinical": ""
    },
    {
        "Accession": "MK995287",
        "Country": "Bangladesh",
        "RecordYear": 2019,
        "IsolateYear": "Not available",
        "Host": "Bat",
        "Specimen": "Not available",
        "IsolateName": "58U",
        "SeqLength": 224,
        "NonClinical": ""
    },
    {
        "Accession": "MK995286",
        "Country": "Bangladesh",
        "RecordYear": 2019,
        "IsolateYear": "Not available",
        "Host": "Bat",
        "Specimen": "Not available",
        "IsolateName": "32US",
        "SeqLength": 224,
        "NonClinical": ""
    },
    {
        "Accession": "MK995285",
        "Country": "Bangladesh",
        "RecordYear": 2019,
        "IsolateYear": "Not available",
        "Host": "Bat",
        "Specimen": "Not available",
        "IsolateName": "26U",
        "SeqLength": 224,
        "NonClinical": ""
    },
    {
        "Accession": "MK995284",
        "Country": "Bangladesh",
        "RecordYear": 2019,
        "IsolateYear": "Not available",
        "Host": "Bat",
        "Specimen": "Not available",
        "IsolateName": "16_RU",
        "SeqLength": 224,
        "NonClinical": ""
    },
    {
        "Accession": "MF133375",
        "Country": "Bangladesh",
        "RecordYear": 2018,
        "IsolateYear": 2014,
        "Host": "Not available",
        "Specimen": "Not available",
        "IsolateName": "NiV/BGD/Swab_Towel/203001/2014",
        "SeqLength": 318,
        "NonClinical": ""
    },
    {
        "Accession": "MF133374",
        "Country": "Bangladesh",
        "RecordYear": 2018,
        "IsolateYear": 2014,
        "Host": "Not available",
        "Specimen": "Not available",
        "IsolateName": "NiV/BGD/Swab_Bed_Rail/503001/2014",
        "SeqLength": 318,
        "NonClinical": ""
    },
    {
        "Accession": "AJ564623",
        "Country": "Malaysia",
        "RecordYear": 2023,
        "IsolateYear": "Not available",
        "Host": "Not available",
        "Specimen": "Not available",
        "IsolateName": "NV/MY/99/UM-0128",
        "SeqLength": 18246,
        "NonClinical": ""
    },
    {
        "Accession": "AJ564622",
        "Country": "Malaysia",
        "RecordYear": 2023,
        "IsolateYear": "Not available",
        "Host": "Not available",
        "Specimen": "Not available",
        "IsolateName": "NV/MY/99/VRI-1413",
        "SeqLength": 18246,
        "NonClinical": ""
    },
    {
        "Accession": "AJ564621",
        "Country": "Malaysia",
        "RecordYear": 2023,
        "IsolateYear": "Not available",
        "Host": "Not available",
        "Specimen": "Not available",
        "IsolateName": "NV/MY/99/VRI-2794",
        "SeqLength": 18246,
        "NonClinical": ""
    },
    {
        "Accession": "NC_002728",
        "Country": "Not available",
        "RecordYear": 2018,
        "IsolateYear": "Not available",
        "Host": "Not available",
        "Specimen": "Not available",
        "IsolateName": "",
        "SeqLength": 18246,
        "NonClinical": ""
    },
    {
        "Accession": "AY029768",
        "Country": "Malaysia",
        "RecordYear": 2001,
        "IsolateYear": "Not available",
        "Host": "Not available",
        "Specimen": "Not available",
        "IsolateName": "UMMC2",
        "SeqLength": 18246,
        "NonClinical": ""
    },
    {
        "Accession": "AY029767",
        "Country": "Malaysia",
        "RecordYear": 2001,
        "IsolateYear": "Not available",
        "Host": "Not available",
        "Specimen": "Not available",
        "IsolateName": "UMMC1",
        "SeqLength": 18246,
        "NonClinical": ""
    },
    {
        "Accession": "AY858111",
        "Country": "Cambodia",
        "RecordYear": 2005,
        "IsolateYear": "Not available",
        "Host": "Bat",
        "Specimen": "Not available",
        "IsolateName": "NiV/KHM/CSUR381",
        "SeqLength": 1809,
        "NonClinical": ""
    },
    {
        "Accession": "AY858110",
        "Country": "Cambodia",
        "RecordYear": 2005,
        "IsolateYear": "Not available",
        "Host": "Bat",
        "Specimen": "Not available",
        "IsolateName": "NiV/KHM/CSUR381",
        "SeqLength": 1599,
        "NonClinical": ""
    },
    {
        "Accession": "AF376747",
        "Country": "Malaysia",
        "RecordYear": 2002,
        "IsolateYear": "Not available",
        "Host": "Not available",
        "Specimen": "Not available",
        "IsolateName": "",
        "SeqLength": 11200,
        "NonClinical": ""
    },
    {
        "Accession": "AF212302",
        "Country": "Not available",
        "RecordYear": 2001,
        "IsolateYear": "Not available",
        "Host": "Not available",
        "Specimen": "Not available",
        "IsolateName": "",
        "SeqLength": 18246,
        "NonClinical": ""
    },
    {
        "Accession": "AF238467",
        "Country": "Not available",
        "RecordYear": 2000,
        "IsolateYear": "Not available",
        "Host": "Not available",
        "Specimen": "Not available",
        "IsolateName": "",
        "SeqLength": 2546,
        "NonClinical": ""
    },
    {
        "Accession": "AF238466",
        "Country": "Not available",
        "RecordYear": 2000,
        "IsolateYear": "Not available",
        "Host": "Not available",
        "Specimen": "Not available",
        "IsolateName": "",
        "SeqLength": 2337,
        "NonClinical": ""
    },
    {
        "Accession": "AJ627196",
        "Country": "Malaysia",
        "RecordYear": 2005,
        "IsolateYear": "Not available",
        "Host": "Pig",
        "Specimen": "Pig",
        "IsolateName": "NV/MY/99/VRI-0626",
        "SeqLength": 18246,
        "NonClinical": ""
    }
]